hopybox/__init__.py
hopybox/__main__.py
hopybox/basedtool.py
hopybox/caculate.py
hopybox/clear.py
hopybox/command.py
hopybox/connect.py
hopybox/debug.py
hopybox/device.py
hopybox/download.py
hopybox/filetool.py
hopybox/headers.py
hopybox/helps.py
hopybox/hopter.py
hopybox/mail.py
hopybox/prompt.py
hopybox/qqget.py
hopybox/scan.py
hopybox/system.py
hopybox/timetool.py
hopybox/translate.py
hopybox/tree_dir.py
hopybox/update.py
HOPYBOX-1.7.0.dist-info/LICENSE
HOPYBOX-1.7.0.dist-info/METADATA
HOPYBOX-1.7.0.dist-info/WHEEL
HOPYBOX-1.7.0.dist-info/entry_points.txt
HOPYBOX-1.7.0.dist-info/top_level.txt
HOPYBOX-1.7.0.dist-info/RECORD
