Metadata-Version: 2.1
Name: HOPYBOX
Version: 1.7.0
Summary: This is an open source, practical command Python box.
Home-page: https://github.com/HOStudio123/HOPYBOX
Author: ChenJinlin
Author-email: hostudio.hopybox@foxmail.com
License: GPL-3.0-or-later
Classifier: Programming Language :: Python :: 3
Classifier: Programming Language :: Python :: 3.7
Classifier: Programming Language :: Python :: 3.8
Classifier: Programming Language :: Python :: 3.9
Classifier: Programming Language :: Python :: 3.10
Classifier: Programming Language :: Python :: 3.11
Classifier: Operating System :: OS Independent
Requires-Python: >=3.7
License-File: LICENSE
Requires-Dist: requests
Requires-Dist: filetype
Requires-Dist: yagmail
Requires-Dist: rich
Requires-Dist: bs4
Requires-Dist: chardet
Requires-Dist: psutil >=5.8.0
